.gitignore
MANIFEST.in
README.txt
setup.cfg
setup.py
anz/__init__.py
anz.casclient.egg-info/PKG-INFO
anz.casclient.egg-info/SOURCES.txt
anz.casclient.egg-info/dependency_links.txt
anz.casclient.egg-info/entry_points.txt
anz.casclient.egg-info/namespace_packages.txt
anz.casclient.egg-info/not-zip-safe
anz.casclient.egg-info/requires.txt
anz.casclient.egg-info/top_level.txt
anz/casclient/__init__.py
anz/casclient/assertion.py
anz/casclient/casclient.py
anz/casclient/configure.zcml
anz/casclient/events.py
anz/casclient/exceptions.py
anz/casclient/interfaces.py
anz/casclient/principal.py
anz/casclient/proxygrantingticketstorage.py
anz/casclient/proxyretriever.py
anz/casclient/sessionmappingstorage.py
anz/casclient/utils.py
anz/casclient/validationspecification.py
anz/casclient/proxyauthexample/__init__.py
anz/casclient/proxyauthexample/configure.zcml
anz/casclient/proxyauthexample/interfaces.py
anz/casclient/proxyauthexample/view.py
anz/casclient/www/add_anzcasclient_form.pt
anz/casclient/www/anz_casclient.png
docs/HISTORY.txt
docs/INSTALL.txt
docs/LICENSE.GPL
docs/LICENSE.txt