Metadata-Version: 1.1
Name: anz.casclient
Version: 1.1.1
Summary: This is a Zope PAS plugin that authenticates users against a CAS (Central Authentication Service) server.
Home-page: http://plone.org/products/anz.casclient/
Author: jiangdongjin
Author-email: eastxing@gmail.com
License: GPL
Keywords: plone cas sso
Platform: UNKNOWN
Classifier: Framework :: Plone
Classifier: Programming Language :: Python
